django_base_library/__init__.py
django_base_library/admin.py
django_base_library/models.py
django_base_library/utilities.py
tw_django_base_library-1.3.0.dist-info/LICENSE
tw_django_base_library-1.3.0.dist-info/METADATA
tw_django_base_library-1.3.0.dist-info/WHEEL
tw_django_base_library-1.3.0.dist-info/top_level.txt
tw_django_base_library-1.3.0.dist-info/RECORD
