Metadata-Version: 2.2
Name: tw_django_base_library
Version: 1.3.0
Summary: A library for setting up a django project according to Techwalnut innovations LLP guidelines
Home-page: https://gitlab.com/dev2_techwalnut/tw-django-base-library.git
Author: Rohit Hazare
Author-email: rohit@techwalnut.com
Classifier: Framework :: Django
Classifier: Programming Language :: Python :: 3
Classifier: License :: OSI Approved :: MIT License
Classifier: Operating System :: OS Independent
Requires-Python: >=3.8
License-File: LICENSE
Requires-Dist: Django>=4.2
Requires-Dist: asgiref==3.7.2
Requires-Dist: boto3==1.35.21
Requires-Dist: botocore==1.35.21
Requires-Dist: certifi==2024.2.2
Requires-Dist: cffi==1.16.0
Requires-Dist: charset-normalizer==3.3.2
Requires-Dist: cryptography==42.0.5
Requires-Dist: defusedxml==0.7.1
Requires-Dist: diff-match-patch==20230430
Requires-Dist: django-cors-headers==4.3.1
Requires-Dist: django-import-export==3.3.7
Requires-Dist: django-phonenumber-field==7.3.0
Requires-Dist: django-storages==1.14.2
Requires-Dist: djangorestframework==3.14.0
Requires-Dist: et-xmlfile==1.1.0
Requires-Dist: gunicorn==23.0.0
Requires-Dist: idna==3.6
Requires-Dist: jmespath==1.0.1
Requires-Dist: MarkupPy==1.14
Requires-Dist: odfpy==1.4.1
Requires-Dist: openpyxl==3.1.2
Requires-Dist: packaging==24.1
Requires-Dist: phonenumbers==8.13.30
Requires-Dist: pillow==10.2.0
Requires-Dist: pycparser==2.21
Requires-Dist: PyJWT==2.8.0
Requires-Dist: PyMySQL==1.1.0
Requires-Dist: python-dateutil==2.9.0.post0
Requires-Dist: python-decouple==3.8
Requires-Dist: pytz==2024.1
Requires-Dist: PyYAML==6.0.1
Requires-Dist: requests==2.31.0
Requires-Dist: s3transfer==0.10.2
Requires-Dist: six==1.16.0
Requires-Dist: sqlparse==0.4.4
Requires-Dist: tablib==3.5.0
Requires-Dist: typing_extensions==4.9.0
Requires-Dist: tzdata==2024.1
Requires-Dist: urllib3==2.2.1
Requires-Dist: xlrd==2.0.1
Requires-Dist: xlwt==1.3.0
Dynamic: author
Dynamic: author-email
Dynamic: classifier
Dynamic: description
Dynamic: description-content-type
Dynamic: home-page
Dynamic: requires-dist
Dynamic: requires-python
Dynamic: summary
